elusion/briq/__init__.py
elusion/briq/client.py
elusion/briq/config.py
elusion/briq/exceptions.py
elusion/briq/py.typed
elusion/briq/http/__init__.py
elusion/briq/http/client.py
elusion/briq/models/__init__.py
elusion/briq/models/campaign.py
elusion/briq/models/common.py
elusion/briq/models/message.py
elusion/briq/models/workspace.py
elusion/briq/services/__init__.py
elusion/briq/services/base.py
elusion/briq/services/campaigns.py
elusion/briq/services/messages.py
elusion/briq/services/workspaces.py
elusion/briq/utils/__init__.py
elusion/briq/utils/helpers.py
elusion/briq/utils/validation.py
briq_sdk-0.0.2.dist-info/METADATA
briq_sdk-0.0.2.dist-info/WHEEL
briq_sdk-0.0.2.dist-info/licenses/LICENSE
briq_sdk-0.0.2.dist-info/RECORD
