Metadata-Version: 2.4
Name: briq-sdk
Version: 0.0.2
Summary: A modern Python SDK for the Briq SMS API
Project-URL: Homepage, https://github.com/elusionhub/briq-python-sdk
Project-URL: Documentation, https://github.com/elusionhub/briq-python-sdk#readme
Project-URL: Repository, https://github.com/elusionhub/briq-python-sdk.git
Project-URL: Issues, https://github.com/elusionhub/briq-python-sdk/issues
Project-URL: Changelog, https://github.com/elusionhub/briq-python-sdk/blob/main/CHANGELOG.md
Author-email: Elution Hub <elusion.lab@gmail.com>
Maintainer-email: Elution Hub <elusion.lab@gmail.com>
License-Expression: MIT
License-File: LICENSE
Keywords: api,briq,communications,messaging,notifications,sdk,sms,text-messaging
Classifier: Development Status :: 4 - Beta
Classifier: Intended Audience :: Developers
Classifier: License :: OSI Approved :: MIT License
Classifier: Operating System :: OS Independent
Classifier: Programming Language :: Python :: 3
Classifier: Programming Language :: Python :: 3.8
Classifier: Programming Language :: Python :: 3.9
Classifier: Programming Language :: Python :: 3.10
Classifier: Programming Language :: Python :: 3.11
Classifier: Programming Language :: Python :: 3.12
Classifier: Topic :: Communications
Classifier: Topic :: Software Development :: Libraries :: Python Modules
Classifier: Typing :: Typed
Requires-Python: >=3.8
Requires-Dist: httpx>=0.25.0
Requires-Dist: pydantic>=2.0.0
Requires-Dist: python-dotenv>=1.0.0
Requires-Dist: typing-extensions>=4.0.0; python_version < '3.11'
Provides-Extra: dev
Requires-Dist: black>=23.0.0; extra == 'dev'
Requires-Dist: mypy>=1.0.0; extra == 'dev'
Requires-Dist: pre-commit>=3.0.0; extra == 'dev'
Requires-Dist: pytest-asyncio>=0.21.0; extra == 'dev'
Requires-Dist: pytest-cov>=4.0.0; extra == 'dev'
Requires-Dist: pytest-mock>=3.10.0; extra == 'dev'
Requires-Dist: pytest>=7.0.0; extra == 'dev'
Requires-Dist: respx>=0.20.0; extra == 'dev'
Requires-Dist: ruff>=0.1.0; extra == 'dev'
Provides-Extra: docs
Requires-Dist: mkdocs-material>=9.0.0; extra == 'docs'
Requires-Dist: mkdocs>=1.5.0; extra == 'docs'
Requires-Dist: mkdocstrings[python]>=0.20.0; extra == 'docs'
Provides-Extra: examples
Requires-Dist: asyncio; extra == 'examples'
